DiaModality/ModalityPlot.py
DiaModality/__init__.py
DiaModality/__main__.py
DiaModality/_version.py
DiaModality-0.2.6.dist-info/LICENSE
DiaModality-0.2.6.dist-info/METADATA
DiaModality-0.2.6.dist-info/WHEEL
DiaModality-0.2.6.dist-info/top_level.txt
DiaModality-0.2.6.dist-info/RECORD
