Metadata-Version: 2.2
Name: DiaModality
Version: 0.2.6
Summary: Tool to plot modality vector diagrams
Author-email: konung-yaropolk <yaropolk1995@gmail.com>
License: MIT License
Project-URL: Homepage, https://github.com/konung-yaropolk/DiaModality
Project-URL: Repository, https://github.com/konung-yaropolk/DiaModality.git
Project-URL: Issues, https://github.com/konung-yaropolk/DiaModality/issues
Keywords: Visualization,Science,Plotting,Matplotlib
Classifier: Programming Language :: Python
Classifier: Programming Language :: Python :: 3
Classifier: Programming Language :: Python :: 3.12
Classifier: License :: OSI Approved :: MIT License
Classifier: Operating System :: OS Independent
Classifier: Development Status :: 4 - Beta
Classifier: Intended Audience :: Science/Research
Classifier: Natural Language :: English
Classifier: Topic :: Scientific/Engineering :: Visualization
Requires-Python: >=3.10
License-File: LICENSE
Requires-Dist: numpy
Requires-Dist: matplotlib
Requires-Dist: scsv>=0.1.4
